netcfgbu/__init__.py
netcfgbu/aiofut.py
netcfgbu/config.py
netcfgbu/config_model.py
netcfgbu/consts.py
netcfgbu/filetypes.py
netcfgbu/filtering.py
netcfgbu/inventory.py
netcfgbu/jumphosts.py
netcfgbu/linter.py
netcfgbu/logger.py
netcfgbu/os_specs.py
netcfgbu/plugins.py
netcfgbu/probe.py
netcfgbu/cli/__init__.py
netcfgbu/cli/backup.py
netcfgbu/cli/inventory.py
netcfgbu/cli/lint.py
netcfgbu/cli/login.py
netcfgbu/cli/main.py
netcfgbu/cli/probe.py
netcfgbu/cli/report.py
netcfgbu/cli/root.py
netcfgbu/cli/vcs.py
netcfgbu/connectors/__init__.py
netcfgbu/connectors/basic.py
netcfgbu/connectors/ssh.py
netcfgbu/vcs/__init__.py
netcfgbu/vcs/git.py
netcfgbu-0.8.0.data/scripts/netcfgbu
tests/__init__.py
tests/conftest.py
tests/test_cli_inventory.py
tests/test_cli_probe.py
tests/test_cli_vcs.py
tests/test_config.py
tests/test_connectors.py
tests/test_filetypes.py
tests/test_filtering.py
tests/test_inventory.py
tests/test_jumphosts.py
tests/test_linters.py
tests/test_os_name.py
tests/test_os_name_prompt_pattern.py
tests/test_plugins.py
tests/test_probe.py
tests/test_vcs.py
netcfgbu-0.8.0.dist-info/LICENSE
netcfgbu-0.8.0.dist-info/METADATA
netcfgbu-0.8.0.dist-info/WHEEL
netcfgbu-0.8.0.dist-info/top_level.txt
netcfgbu-0.8.0.dist-info/RECORD
