Metadata-Version: 2.1
Name: netcfgbu
Version: 0.8.0
Summary: Network Configuration Backup
Home-page: UNKNOWN
Author: Jeremy Schulman
License: UNKNOWN
Platform: UNKNOWN
Classifier: Development Status :: 4 - Beta
Classifier: Intended Audience :: Developers
Classifier: License :: OSI Approved :: Apache Software License
Classifier: Operating System :: MacOS :: MacOS X
Classifier: Operating System :: POSIX
Classifier: Programming Language :: Python :: 3.8
Classifier: Topic :: Software Development :: Libraries :: Python Modules
Classifier: Topic :: System :: Networking
Requires-Dist: aiofiles (~=0.5.0)
Requires-Dist: asyncssh (~=2.2.1)
Requires-Dist: toml (~=0.10.1)
Requires-Dist: invoke (~=1.4.1)
Requires-Dist: pydantic (~=1.5.1)
Requires-Dist: tabulate (~=0.8.7)
Requires-Dist: click (~=7.1.2)
Requires-Dist: first (~=2.0.2)
Requires-Dist: pexpect (~=4.8.0)
